{
  "TEI": {
    "@xmlns": "http://www.tei-c.org/ns/1.0",
    "teiHeader": {
      "fileDesc": {
        "titleStmt": {
          "title": "Description of Free Library of Philadelphia, Lewis M 450: Drawing of Sri Kishu"
        },
        "publicationStmt": {
          "publisher": "Free Library of Philadelphia",
          "availability": {
            "licence": [
              {
                "@target": "http://creativecommons.org/publicdomain/mark/1.0/",
                "#text": "These images and the content of Free Library of Philadelphia Lewis M 450: Drawing of Sri Kishu are free of known copyright restrictions and in the public domain. See the Creative Commons Public Domain Mark page for usage details, http://creativecommons.org/publicdomain/mark/1.0/."
              },
              {
                "@target": "https://creativecommons.org/publicdomain/zero/1.0/legalcode",
                "#text": "To the extent possible under law, Free Library of Philadelphia, Special Collections has waived all copyright and related or neighboring rights to this metadata about Free Library of Philadelphia Lewis M 450: Drawing of Sri Kishu. This work is published from: United States. For a summary of CC0, see https://creativecommons.org/publicdomain/zero/1.0/. Legal code: https://creativecommons.org/publicdomain/zero/1.0/legalcode."
              }
            ]
          }
        },
        "sourceDesc": {
          "msDesc": {
            "msIdentifier": {
              "country": "United States",
              "settlement": "Philadelphia",
              "repository": "Free Library of Philadelphia",
              "collection": "John Frederick Lewis collection of Oriental Manuscripts",
              "idno": {
                "@type": "call-number",
                "#text": "Lewis M 450"
              }
            },
            "msContents": {
              "summary": null,
              "textLang": {
                "@mainLang": "zxx",
                "#text": "No linguistic content, Not applicable"
              },
              "msItem": {
                "title": "Drawing of Sri Kishu",
                "respStmt": {
                  "resp": "former owner",
                  "persName": {
                    "@ref": "https://viaf.org/viaf/63874811",
                    "#text": "Lewis, John Frederick, 1860-1932"
                  }
                }
              }
            },
            "physDesc": {
              "objectDesc": {
                "supportDesc": {
                  "extent": "9.5 x 12.5 cm"
                }
              }
            }
          }
        }
      },
      "profileDesc": {
        "textClass": null
      }
    },
    "facsimile": {
      "surface": [
        {
          "@n": "Lewis M 450 front",
          "graphic": [
            {
              "@height": "4011px",
              "@url": "master/11079_0000.tif",
              "@width": "2945px"
            },
            {
              "@height": "190px",
              "@url": "thumb/11079_0000_thumb.jpg",
              "@width": "139px"
            },
            {
              "@height": "1800px",
              "@url": "web/11079_0000_web.jpg",
              "@width": "1321px"
            }
          ]
        },
        {
          "@n": "Lewis M 450 reverse",
          "graphic": [
            {
              "@height": "3983px",
              "@url": "master/11079_0001.tif",
              "@width": "2910px"
            },
            {
              "@height": "190px",
              "@url": "thumb/11079_0001_thumb.jpg",
              "@width": "138px"
            },
            {
              "@height": "1800px",
              "@url": "web/11079_0001_web.jpg",
              "@width": "1315px"
            }
          ]
        }
      ]
    }
  }
}